gnssmapper/__init__.py
gnssmapper/geo.py
gnssmapper/log.py
gnssmapper/observations.py
gnssmapper/satellitedata.py
gnssmapper/sim.py
gnssmapper/algo/FPL.py
gnssmapper/algo/__init__.py
gnssmapper/algo/main.py
gnssmapper/common/__init__.py
gnssmapper/common/check.py
gnssmapper/common/constants.py
gnssmapper/common/io.py
gnssmapper/common/time.py
gnssmapper/data/__init__.py
gnssmapper/data/orbits/__init__.py
gnssmapper/data/sp3/__init__.py
gnssmapper-0.0.1a6.dist-info/LICENCE
gnssmapper-0.0.1a6.dist-info/METADATA
gnssmapper-0.0.1a6.dist-info/WHEEL
gnssmapper-0.0.1a6.dist-info/top_level.txt
gnssmapper-0.0.1a6.dist-info/RECORD
