Metadata-Version: 2.1
Name: gnssmapper
Version: 0.0.1a6
Summary: A package for generating 3D maps from gnss data
Home-page: https://github.com/TerryLines/gnssmapper
Author: Terry Lines
Author-email: terence.lines@glasgow.ac.uk
License: UNKNOWN
Platform: UNKNOWN
Classifier: Programming Language :: Python :: 3
Classifier: License :: OSI Approved :: MIT License
Classifier: Operating System :: OS Independent
Requires-Python: >=3.7
License-File: LICENCE
Requires-Dist: geopandas (>=0.8)
Requires-Dist: pygeos (>=0.9)
Requires-Dist: scipy
Requires-Dist: numpy
Requires-Dist: shapely
Requires-Dist: pyproj (>=2.2)
